maillib/__init__.py
maillib/admin.py
maillib/apps.py
maillib/models.py
maillib/urls.py
maillib/views.py
maillib/migrations/__init__.py
maillib/tests/__init__.py
maillib/tests/test_urls.py
maillib/tests/test_views.py
Dowell_Mail-1.0.2.dist-info/LICENCE
Dowell_Mail-1.0.2.dist-info/LICENSE
Dowell_Mail-1.0.2.dist-info/METADATA
Dowell_Mail-1.0.2.dist-info/WHEEL
Dowell_Mail-1.0.2.dist-info/top_level.txt
Dowell_Mail-1.0.2.dist-info/RECORD
