Metadata-Version: 2.1
Name: Dowell-Mail
Version: 1.0.2
Summary: Dowell Mail Package
Author: Marvin
Author-email: marvin.wekesa@gmail.com
Keywords: Dowell Django Mail
Classifier: Development Status :: 4 - Beta
Classifier: Framework :: Django
Classifier: Intended Audience :: Developers
Classifier: License :: OSI Approved :: MIT License
Classifier: Operating System :: OS Independent
Classifier: Programming Language :: Python
Classifier: Programming Language :: Python :: 3
Classifier: Programming Language :: Python :: 3 :: Only
Classifier: Programming Language :: Python :: 3.8
Classifier: Programming Language :: Python :: 3.9
Requires-Python: >=3.8
License-File: LICENCE
License-File: LICENSE
Requires-Dist: Django (>=3)
Requires-Dist: requests (>=2.25.1)
Provides-Extra: dev
Requires-Dist: unittest ; extra == 'dev'
